flask_debugtool/__init__.py
flask_debugtool/compat.py
flask_debugtool/debug_panel.py
flask_debugtool/toolbar.py
flask_debugtool/utils.py
flask_debugtool/panels/__init__.py
flask_debugtool/panels/config_vars.py
flask_debugtool/panels/headers.py
flask_debugtool/panels/lineprofiler.py
flask_debugtool/panels/logger.py
flask_debugtool/panels/profiler.py
flask_debugtool/panels/request_vars.py
flask_debugtool/panels/sqlalchemy.py
flask_debugtool/panels/template.py
flask_debugtool/panels/timer.py
flask_debugtool/panels/versions.py
Flask_DebugTool-0.1.6.dist-info/DESCRIPTION.rst
Flask_DebugTool-0.1.6.dist-info/METADATA
Flask_DebugTool-0.1.6.dist-info/metadata.json
Flask_DebugTool-0.1.6.dist-info/RECORD
Flask_DebugTool-0.1.6.dist-info/top_level.txt
Flask_DebugTool-0.1.6.dist-info/WHEEL
