Metadata-Version: 2.0
Name: Flask-DebugTool
Version: 0.1.6
Summary: A toolbar overlay for debugging Flask applications.
Home-page: https://github.com/lufeng4828/flask_debugtool
Author: Feng Lu
Author-email: lufeng044@qq.com
License: BSD
Platform: any
Classifier: Development Status :: 4 - Beta
Classifier: Environment :: Web Environment
Classifier: Intended Audience :: Developers
Classifier: License :: OSI Approved :: BSD License
Classifier: Operating System :: OS Independent
Classifier: Programming Language :: Python
Classifier: Topic :: Internet :: WWW/HTTP :: Dynamic Content
Classifier: Topic :: Software Development :: Libraries :: Python Modules
Requires-Dist: Flask (>=0.8)
Requires-Dist: Blinker
Requires-Dist: itsdangerous
Requires-Dist: werkzeug
